mobvoi_tts_mcp/__init__.py
mobvoi_tts_mcp/server.py
mobvoi_tts_mcp/utils.py
mobvoi_tts_sdk/__init__.py
mobvoi_tts_sdk/client.py
mobvoi_tts_sdk/play.py
mobvoi_tts_sdk/text_to_speech/__init__.py
mobvoi_tts_sdk/text_to_speech/client.py
mobvoi_tts_sdk/voice_clone/__init__.py
mobvoi_tts_sdk/voice_clone/client.py
mobvoi_tts_mcp-0.1.4.dist-info/METADATA
mobvoi_tts_mcp-0.1.4.dist-info/WHEEL
mobvoi_tts_mcp-0.1.4.dist-info/entry_points.txt
mobvoi_tts_mcp-0.1.4.dist-info/licenses/LICENSE
mobvoi_tts_mcp-0.1.4.dist-info/RECORD
