Metadata-Version: 2.4
Name: mobvoi-tts-mcp
Version: 0.1.4
Summary: Mobvoi TTS MCP Server
License: MIT License
License-File: LICENSE
Keywords: mcp,mobvoi,text-to-speech,tts,voice-cloning
Requires-Python: >=3.10
Requires-Dist: fastapi==0.109.2
Requires-Dist: fuzzywuzzy>=0.18.0
Requires-Dist: httpx>=0.28.1
Requires-Dist: mcp[cli]>=1.6.0
Requires-Dist: pydantic>=2.6.1
Requires-Dist: pytest>=8.0.0
Requires-Dist: python-dotenv==1.0.1
Requires-Dist: sounddevice>=0.5.1
Requires-Dist: soundfile>=0.13.1
Requires-Dist: uvicorn==0.27.1
Provides-Extra: dev
Requires-Dist: build>=1.0.3; extra == 'dev'
Requires-Dist: fastmcp==0.4.1; extra == 'dev'
Requires-Dist: pre-commit==3.6.2; extra == 'dev'
Requires-Dist: pytest-cov==4.1.0; extra == 'dev'
Requires-Dist: pytest==8.0.0; extra == 'dev'
Requires-Dist: ruff==0.3.0; extra == 'dev'
Requires-Dist: twine==6.1.0; extra == 'dev'
